logging_service/__init__.py
logging_service/logging_service.py
logging_service/test/__init__.py
logging_service/test/test_logging_singleton.py
logging_singleton-1.0.4.dist-info/METADATA
logging_singleton-1.0.4.dist-info/WHEEL
logging_singleton-1.0.4.dist-info/top_level.txt
logging_singleton-1.0.4.dist-info/RECORD
