Metadata-Version: 2.4
Name: logging-singleton
Version: 1.0.4
Summary: Logger shared by all modules in a program. Simplification of standard Python logging
Author-email: Andreas Paepcke <paepcke@cs.stanford.edu>
Maintainer-email: Andreas Paepcke <paepcke@cs.stanford.edu>
License: MIT License
Project-URL: Homepage, https://github.com/paepcke/logging_singleton
Project-URL: Documentation, https://github.com/paepcke/logging_singleton
Project-URL: Changelog, https://github.com/paepcke/logging_singleton/blob/master/CHANGELOG.md
Project-URL: Repository, https://github.com/paepcke/logging_singleton
Requires-Python: >=3.5
Provides-Extra: test
Requires-Dist: pytest>=9.0.2; extra == "test"
